<?xml version="1.0" encoding="UTF-8"?>
<multicast version="1606">
    <corpus c_name="persian">
        <text t_name="g1-m-06" annotators="Shirin Adibifar" speaker="PS06">
            <file f_name="mc_persian_g1-m-06" audio="mc_persian_g1-m-06.wav" updated="2016-06-23">
                <unit uid="0001" start_time="691" end_time="7876">
                    <utterance_id>persian_g1-m-06_0001</utterance_id>
                    <utterance>Yek mazrae bud yeki ham dar hāle čidane golābi bālāye deraxt bude</utterance>
                    <utterance_translation>There was a farm where a man was picking pears on a tree</utterance_translation>
                    <annotations>
                        <segment>
                            <gword>#</gword>
                            <gloss>#</gloss>
                            <graid>#</graid>
                        </segment>
                        <segment>
                            <gword>Yek</gword>
                            <gloss>one</gloss>
                            <graid>ln_deti</graid>
                        </segment>
                        <segment>
                            <gword>mazrae</gword>
                            <gloss>farm</gloss>
                            <graid>np:s</graid>
                        </segment>
                        <segment>
                            <gword>bud</gword>
                            <gloss>be.pst.3sg</gloss>
                            <graid>predex</graid>
                        </segment>
                        <segment>
                            <gword>#</gword>
                            <gloss>#</gloss>
                            <graid>#</graid>
                        </segment>
                        <segment>
                            <gword>yeki</gword>
                            <gloss>one</gloss>
                            <graid>ind_pro.h:a</graid>
                        </segment>
                        <segment>
                            <gword>ham</gword>
                            <gloss>add</gloss>
                            <graid>other</graid>
                        </segment>
                        <segment>
                            <gword>dar</gword>
                            <gloss>in</gloss>
                            <graid>other</graid>
                        </segment>
                        <segment>
                            <gword>hāle</gword>
                            <gloss>condition.of</gloss>
                            <graid>other</graid>
                        </segment>
                        <segment>
                            <gword>čidane</gword>
                            <gloss>picking</gloss>
                            <graid>vother</graid>
                        </segment>
                        <segment>
                            <gword>golābi</gword>
                            <gloss>pear</gloss>
                            <graid>np:p</graid>
                        </segment>
                        <segment>
                            <gword>#</gword>
                            <gloss>#</gloss>
                            <graid>#</graid>
                        </segment>
                        <segment>
                            <gword>0</gword>
                            <gloss>0</gloss>
                            <graid>0.h:s</graid>
                        </segment>
                        <segment>
                            <gword>bālāye</gword>
                            <gloss>top.of</gloss>
                            <graid>adp</graid>
                        </segment>
                        <segment>
                            <gword>deraxt</gword>
                            <gloss>tree</gloss>
                            <graid>np:l</graid>
                        </segment>
                        <segment>
                            <gword>bude</gword>
                            <gloss>be.pst.3sg</gloss>
                            <graid>cop</graid>
                        </segment>
                    </annotations>
                </unit>
                <unit uid="0002" start_time="7876" end_time="10898">
                    <utterance_id>persian_g1-m-06_0002</utterance_id>
                    <utterance>golābiha rā āvarde bud pāyin rixt tuye sabad</utterance>
                    <utterance_translation>he brought the pears down and put all in a basket</utterance_translation>
                    <annotations>
                        <segment>
                            <gword>#</gword>
                            <gloss>#</gloss>
                            <graid>#</graid>
                        </segment>
                        <segment>
                            <gword>0</gword>
                            <gloss>0</gloss>
                            <graid>0.h:a</graid>
                        </segment>
                        <segment>
                            <gword>golābiha</gword>
                            <gloss>pear.pl</gloss>
                            <graid>np:p</graid>
                        </segment>
                        <segment>
                            <gword>=rā</gword>
                            <gloss>=acc</gloss>
                            <graid>=acc_rn</graid>
                        </segment>
                        <segment>
                            <gword>āvarde</gword>
                            <gloss>bring.pst.ptcp</gloss>
                            <graid>v:pred</graid>
                        </segment>
                        <segment>
                            <gword>bud</gword>
                            <gloss>aux.pst.3sg</gloss>
                            <graid>aux</graid>
                        </segment>
                        <segment>
                            <gword>pāyin</gword>
                            <gloss>down</gloss>
                            <graid>rv</graid>
                        </segment>
                        <segment>
                            <gword>#</gword>
                            <gloss>#</gloss>
                            <graid>#</graid>
                        </segment>
                        <segment>
                            <gword>0</gword>
                            <gloss>0</gloss>
                            <graid>0.h:a</graid>
                        </segment>
                        <segment>
                            <gword>rixt</gword>
                            <gloss>pour.pst.3sg</gloss>
                            <graid>v:pred</graid>
                        </segment>
                        <segment>
                            <gword>0</gword>
                            <gloss>0</gloss>
                            <graid>0:p</graid>
                        </segment>
                        <segment>
                            <gword>tuye</gword>
                            <gloss>inside</gloss>
                            <graid>adp</graid>
                        </segment>
                        <segment>
                            <gword>sabad</gword>
                            <gloss>basket</gloss>
                            <graid>np:g</graid>
                        </segment>
                    </annotations>
                </unit>
                <unit uid="0003" start_time="10898" end_time="20315">
                    <utterance_id>persian_g1-m-06_0003</utterance_id>
                    <utterance>bad yeki bā dočarxe az ānjā rad mišode āmade yek golābi bardārad vaseye xordan did kasi nist yek sabade por rā gerefte</utterance>
                    <utterance_translation>somebody was passing, he wanted to take one pear but found out nobody was watching so he took one of the baskets</utterance_translation>
                    <annotations>
                        <segment>
                            <gword>#</gword>
                            <gloss>#</gloss>
                            <graid>#</graid>
                        </segment>
                        <segment>
                            <gword>bad</gword>
                            <gloss>then</gloss>
                            <graid>other</graid>
                        </segment>
                        <segment>
                            <gword>yeki</gword>
                            <gloss>one</gloss>
                            <graid>ind_pro.h:s</graid>
                        </segment>
                        <segment>
                            <gword>bā</gword>
                            <gloss>with</gloss>
                            <graid>adp</graid>
                        </segment>
                        <segment>
                            <gword>dočarxe</gword>
                            <gloss>bike</gloss>
                            <graid>np:obl</graid>
                        </segment>
                        <segment>
                            <gword>az</gword>
                            <gloss>from</gloss>
                            <graid>adp</graid>
                        </segment>
                        <segment>
                            <gword>ānjā</gword>
                            <gloss>there</gloss>
                            <graid>other:l</graid>
                        </segment>
                        <segment>
                            <gword>rad</gword>
                            <gloss>passing</gloss>
                            <graid>lvc</graid>
                        </segment>
                        <segment>
                            <gword>mišode</gword>
                            <gloss>become.pst.indic.3sg</gloss>
                            <graid>v:pred</graid>
                        </segment>
                        <segment>
                            <gword>#</gword>
                            <gloss>#</gloss>
                            <graid>#</graid>
                        </segment>
                        <segment>
                            <gword>0</gword>
                            <gloss>0</gloss>
                            <graid>0.h:a</graid>
                        </segment>
                        <segment>
                            <gword>āmade</gword>
                            <gloss>come.pst.ptcp</gloss>
                            <graid>aux</graid>
                        </segment>
                        <segment>
                            <gword>yek</gword>
                            <gloss>one</gloss>
                            <graid>ln_deti</graid>
                        </segment>
                        <segment>
                            <gword>golābi</gword>
                            <gloss>pear</gloss>
                            <graid>np:p</graid>
                        </segment>
                        <segment>
                            <gword>bardārad</gword>
                            <gloss>pick.up.prs.subj.3sg</gloss>
                            <graid>v:pred</graid>
                        </segment>
                        <segment>
                            <gword>vaseye</gword>
                            <gloss>for</gloss>
                            <graid>other</graid>
                        </segment>
                        <segment>
                            <gword>xordan</gword>
                            <gloss>eating</gloss>
                            <graid>vother</graid>
                        </segment>
                        <segment>
                            <gword>#</gword>
                            <gloss>#</gloss>
                            <graid>#</graid>
                        </segment>
                        <segment>
                            <gword>0</gword>
                            <gloss>0</gloss>
                            <graid>0.h:a</graid>
                        </segment>
                        <segment>
                            <gword>did</gword>
                            <gloss>see.pst.3sg</gloss>
                            <graid>v:pred</graid>
                        </segment>
                        <segment>
                            <gword>#neg.cc:p</gword>
                            <gloss>#neg.cc:p</gloss>
                            <graid>#neg.cc:p</graid>
                        </segment>
                        <segment>
                            <gword>kasi</gword>
                            <gloss>somebody</gloss>
                            <graid>ind_pro.h:s</graid>
                        </segment>
                        <segment>
                            <gword>nist</gword>
                            <gloss>neg.be.prs.3sg</gloss>
                            <graid>predex</graid>
                        </segment>
                        <segment>
                            <gword>#</gword>
                            <gloss>#</gloss>
                            <graid>#</graid>
                        </segment>
                        <segment>
                            <gword>0</gword>
                            <gloss>0</gloss>
                            <graid>0.h:a</graid>
                        </segment>
                        <segment>
                            <gword>yek</gword>
                            <gloss>one</gloss>
                            <graid>ln_deti</graid>
                        </segment>
                        <segment>
                            <gword>sabade</gword>
                            <gloss>basket=ezafe</gloss>
                            <graid>np:p</graid>
                        </segment>
                        <segment>
                            <gword>por</gword>
                            <gloss>full</gloss>
                            <graid>rn_lex</graid>
                        </segment>
                        <segment>
                            <gword>=rā</gword>
                            <gloss>=acc</gloss>
                            <graid>=acc_rn</graid>
                        </segment>
                        <segment>
                            <gword>gerefte</gword>
                            <gloss>get.pst.ptcp</gloss>
                            <graid>v:pred</graid>
                        </segment>
                    </annotations>
                </unit>
                <unit uid="0004" start_time="20315" end_time="22590">
                    <utterance_id>persian_g1-m-06_0004</utterance_id>
                    <utterance>gozāšte ruye dočarxeaš rafte</utterance>
                    <utterance_translation>and put it on his bike and went away</utterance_translation>
                    <annotations>
                        <segment>
                            <gword>#</gword>
                            <gloss>#</gloss>
                            <graid>#</graid>
                        </segment>
                        <segment>
                            <gword>0</gword>
                            <gloss>0</gloss>
                            <graid>0.h:a</graid>
                        </segment>
                        <segment>
                            <gword>gozāšte</gword>
                            <gloss>put.pst.ptcp</gloss>
                            <graid>v:pred</graid>
                        </segment>
                        <segment>
                            <gword>0</gword>
                            <gloss>0</gloss>
                            <graid>0:p</graid>
                        </segment>
                        <segment>
                            <gword>ruye</gword>
                            <gloss>on</gloss>
                            <graid>adp</graid>
                        </segment>
                        <segment>
                            <gword>dočarxe</gword>
                            <gloss>bike</gloss>
                            <graid>np:l</graid>
                        </segment>
                        <segment>
                            <gword>=aš</gword>
                            <gloss>=poss.3sg</gloss>
                            <graid>=pro.h:poss</graid>
                        </segment>
                        <segment>
                            <gword>#</gword>
                            <gloss>#</gloss>
                            <graid>#</graid>
                        </segment>
                        <segment>
                            <gword>0</gword>
                            <gloss>0</gloss>
                            <graid>0.h:s</graid>
                        </segment>
                        <segment>
                            <gword>rafte</gword>
                            <gloss>go.pst.ptcp</gloss>
                            <graid>v:pred</graid>
                        </segment>
                    </annotations>
                </unit>
                <unit uid="0005" start_time="22590" end_time="27905">
                    <utterance_id>persian_g1-m-06_0005</utterance_id>
                    <utterance>vasate rāh ham zamin xorde </utterance>
                    <utterance_translation>on his way he fell down</utterance_translation>
                    <annotations>
                        <segment>
                            <gword>#</gword>
                            <gloss>#</gloss>
                            <graid>#</graid>
                        </segment>
                        <segment>
                            <gword>vasate</gword>
                            <gloss>middle.of</gloss>
                            <graid>adp</graid>
                        </segment>
                        <segment>
                            <gword>rāh</gword>
                            <gloss>way</gloss>
                            <graid>np:l</graid>
                        </segment>
                        <segment>
                            <gword>ham</gword>
                            <gloss>add</gloss>
                            <graid>other</graid>
                        </segment>
                        <segment>
                            <gword>0</gword>
                            <gloss>0</gloss>
                            <graid>0.h:s_cp</graid>
                        </segment>
                        <segment>
                            <gword>zamin</gword>
                            <gloss>ground</gloss>
                            <graid>lvc</graid>
                        </segment>
                        <segment>
                            <gword>xorde</gword>
                            <gloss>eat.pst.ptcp</gloss>
                            <graid>v:pred</graid>
                        </segment>
                    </annotations>
                </unit>
                <unit uid="0006" start_time="27905" end_time="30173">
                    <utterance_id>persian_g1-m-06_0006</utterance_id>
                    <utterance>bad dobāre pā šode </utterance>
                    <utterance_translation>he got up again</utterance_translation>
                    <annotations>
                        <segment>
                            <gword>#</gword>
                            <gloss>#</gloss>
                            <graid>#</graid>
                        </segment>
                        <segment>
                            <gword>bad</gword>
                            <gloss>then</gloss>
                            <graid>other</graid>
                        </segment>
                        <segment>
                            <gword>0</gword>
                            <gloss>0</gloss>
                            <graid>0.h:s</graid>
                        </segment>
                        <segment>
                            <gword>dobāre</gword>
                            <gloss>again</gloss>
                            <graid>other</graid>
                        </segment>
                        <segment>
                            <gword>pā</gword>
                            <gloss>stood</gloss>
                            <graid>lvc</graid>
                        </segment>
                        <segment>
                            <gword>šode</gword>
                            <gloss>become.pst.ptcp</gloss>
                            <graid>v:pred</graid>
                        </segment>
                    </annotations>
                </unit>
                <unit uid="0007" start_time="30173" end_time="33823">
                    <utterance_id>persian_g1-m-06_0007</utterance_id>
                    <utterance>golābihā rā jam karde gozāšte tuye sabad</utterance>
                    <utterance_translation>gathered up all pears and put them back into the basket</utterance_translation>
                    <annotations>
                        <segment>
                            <gword>#</gword>
                            <gloss>#</gloss>
                            <graid>#</graid>
                        </segment>
                        <segment>
                            <gword>0</gword>
                            <gloss>0</gloss>
                            <graid>0.h:a</graid>
                        </segment>
                        <segment>
                            <gword>golābihā</gword>
                            <gloss>pear.pl</gloss>
                            <graid>np:p</graid>
                        </segment>
                        <segment>
                            <gword>=rā</gword>
                            <gloss>=acc</gloss>
                            <graid>=acc_rn</graid>
                        </segment>
                        <segment>
                            <gword>jam</gword>
                            <gloss>collected</gloss>
                            <graid>lvc</graid>
                        </segment>
                        <segment>
                            <gword>karde</gword>
                            <gloss>do.pst.ptcp</gloss>
                            <graid>v:pred</graid>
                        </segment>
                        <segment>
                            <gword>#</gword>
                            <gloss>#</gloss>
                            <graid>#</graid>
                        </segment>
                        <segment>
                            <gword>0</gword>
                            <gloss>0</gloss>
                            <graid>0.h:a</graid>
                        </segment>
                        <segment>
                            <gword>gozāšte</gword>
                            <gloss>put.pst.ptcp</gloss>
                            <graid>v:pred</graid>
                        </segment>
                        <segment>
                            <gword>0</gword>
                            <gloss>0</gloss>
                            <graid>0:p</graid>
                        </segment>
                        <segment>
                            <gword>tuye</gword>
                            <gloss>inside</gloss>
                            <graid>adp</graid>
                        </segment>
                        <segment>
                            <gword>sabad</gword>
                            <gloss>basket</gloss>
                            <graid>np:l</graid>
                        </segment>
                    </annotations>
                </unit>
                <unit uid="0008" start_time="33823" end_time="40915">
                    <utterance_id>persian_g1-m-06_0008</utterance_id>
                    <utterance>bad se nafar az ānjā rad mišodand behešān yek golābi dāde ān se nafar dobāre az ānjāyi ke deraxt bude</utterance>
                    <utterance_translation>there were three boys there to whom the little boy gave a pear each</utterance_translation>
                    <annotations>
                        <segment>
                            <gword>#</gword>
                            <gloss>#</gloss>
                            <graid>#</graid>
                        </segment>
                        <segment>
                            <gword>bad</gword>
                            <gloss>then</gloss>
                            <graid>other</graid>
                        </segment>
                        <segment>
                            <gword>se</gword>
                            <gloss>three</gloss>
                            <graid>ln_qu</graid>
                        </segment>
                        <segment>
                            <gword>nafar</gword>
                            <gloss>person</gloss>
                            <graid>np.h:s</graid>
                        </segment>
                        <segment>
                            <gword>az</gword>
                            <gloss>from</gloss>
                            <graid>adp</graid>
                        </segment>
                        <segment>
                            <gword>ānjā</gword>
                            <gloss>there</gloss>
                            <graid>other:l</graid>
                        </segment>
                        <segment>
                            <gword>rad</gword>
                            <gloss>passing</gloss>
                            <graid>lvc</graid>
                        </segment>
                        <segment>
                            <gword>mišodand</gword>
                            <gloss>become.pst.indic.3pl</gloss>
                            <graid>v:pred</graid>
                        </segment>
                        <segment>
                            <gword>#</gword>
                            <gloss>#</gloss>
                            <graid>#</graid>
                        </segment>
                        <segment>
                            <gword>0</gword>
                            <gloss>0</gloss>
                            <graid>0.h:a</graid>
                        </segment>
                        <segment>
                            <gword>be</gword>
                            <gloss>to</gloss>
                            <graid>adp</graid>
                        </segment>
                        <segment>
                            <gword>=hešān</gword>
                            <gloss>=pro.3pl</gloss>
                            <graid>=pro.h:g</graid>
                        </segment>
                        <segment>
                            <gword>yek</gword>
                            <gloss>one</gloss>
                            <graid>ln_deti</graid>
                        </segment>
                        <segment>
                            <gword>golābi</gword>
                            <gloss>pear</gloss>
                            <graid>np:p</graid>
                        </segment>
                        <segment>
                            <gword>dāde</gword>
                            <gloss>give.pst.ptcp</gloss>
                            <graid>v:pred</graid>
                        </segment>
                        <segment>
                            <gword>#</gword>
                            <gloss>#</gloss>
                            <graid>#</graid>
                        </segment>
                        <segment>
                            <gword>ān</gword>
                            <gloss>that</gloss>
                            <graid>ln_dem</graid>
                        </segment>
                        <segment>
                            <gword>se</gword>
                            <gloss>three</gloss>
                            <graid>ln_qu</graid>
                        </segment>
                        <segment>
                            <gword>nafar</gword>
                            <gloss>person</gloss>
                            <graid>np.h:s</graid>
                        </segment>
                        <segment>
                            <gword>dobāre</gword>
                            <gloss>again</gloss>
                            <graid>other</graid>
                        </segment>
                        <segment>
                            <gword>#nc</gword>
                            <gloss>#nc</gloss>
                            <graid>#nc</graid>
                        </segment>
                        <segment>
                            <gword>az</gword>
                            <gloss>NC</gloss>
                            <graid>nc</graid>
                        </segment>
                        <segment>
                            <gword>ānjāyi</gword>
                            <gloss>NC</gloss>
                            <graid>nc</graid>
                        </segment>
                        <segment>
                            <gword>ke</gword>
                            <gloss>NC</gloss>
                            <graid>nc</graid>
                        </segment>
                        <segment>
                            <gword>deraxt</gword>
                            <gloss>NC</gloss>
                            <graid>nc</graid>
                        </segment>
                        <segment>
                            <gword>bude</gword>
                            <gloss>NC</gloss>
                            <graid>nc</graid>
                        </segment>
                    </annotations>
                </unit>
                <unit uid="0009" start_time="40915" end_time="47417">
                    <utterance_id>persian_g1-m-06_0009</utterance_id>
                    <utterance>rad mišodand va ān kasi ke dārad golābihā rā mikanad āmad pāyin faqat sabade xāli rā mibinad</utterance>
                    <utterance_translation>while the boys were passing, the man who was picking pears on the tree came down and found an empty basket</utterance_translation>
                    <annotations>
                        <segment>
                            <gword>%</gword>
                            <gloss>%</gloss>
                            <graid>%</graid>
                        </segment>
                        <segment>
                            <gword>rad</gword>
                            <gloss>passing</gloss>
                            <graid>lvc</graid>
                        </segment>
                        <segment>
                            <gword>mišodand</gword>
                            <gloss>become.pst.indic.3pl</gloss>
                            <graid>v:pred</graid>
                        </segment>
                        <segment>
                            <gword>#</gword>
                            <gloss>#</gloss>
                            <graid>#</graid>
                        </segment>
                        <segment>
                            <gword>va</gword>
                            <gloss>and</gloss>
                            <graid>other</graid>
                        </segment>
                        <segment>
                            <gword>ān</gword>
                            <gloss>that</gloss>
                            <graid>ln_dem</graid>
                        </segment>
                        <segment>
                            <gword>kasi</gword>
                            <gloss>somebody</gloss>
                            <graid>ind_pro.h:s</graid>
                        </segment>
                        <segment>
                            <gword>ke</gword>
                            <gloss>that</gloss>
                            <graid>ke</graid>
                        </segment>
                        <segment>
                            <gword>#rc</gword>
                            <gloss>#rc</gloss>
                            <graid>#rc</graid>
                        </segment>
                        <segment>
                            <gword>dārad</gword>
                            <gloss>aux.prs.3sg</gloss>
                            <graid>aux</graid>
                        </segment>
                        <segment>
                            <gword>golābihā</gword>
                            <gloss>pear.pl</gloss>
                            <graid>np:p</graid>
                        </segment>
                        <segment>
                            <gword>=rā</gword>
                            <gloss>=acc</gloss>
                            <graid>=acc_rn</graid>
                        </segment>
                        <segment>
                            <gword>mikanad</gword>
                            <gloss>pick.prs.indic.3sg</gloss>
                            <graid>v:pred</graid>
                        </segment>
                        <segment>
                            <gword>%</gword>
                            <gloss>%</gloss>
                            <graid>%</graid>
                        </segment>
                        <segment>
                            <gword>āmad</gword>
                            <gloss>come.pst.3sg</gloss>
                            <graid>v:pred</graid>
                        </segment>
                        <segment>
                            <gword>pāyin</gword>
                            <gloss>down</gloss>
                            <graid>rv</graid>
                        </segment>
                        <segment>
                            <gword>#</gword>
                            <gloss>#</gloss>
                            <graid>#</graid>
                        </segment>
                        <segment>
                            <gword>0</gword>
                            <gloss>0</gloss>
                            <graid>0.h:a</graid>
                        </segment>
                        <segment>
                            <gword>faqat</gword>
                            <gloss>only</gloss>
                            <graid>other</graid>
                        </segment>
                        <segment>
                            <gword>sabade</gword>
                            <gloss>basket=ezafe</gloss>
                            <graid>np:p</graid>
                        </segment>
                        <segment>
                            <gword>xāli</gword>
                            <gloss>empty</gloss>
                            <graid>rn_lex</graid>
                        </segment>
                        <segment>
                            <gword>=rā</gword>
                            <gloss>=acc</gloss>
                            <graid>=acc_rn</graid>
                        </segment>
                        <segment>
                            <gword>mibinad</gword>
                            <gloss>see.prs.indic.3sg</gloss>
                            <graid>v:pred</graid>
                        </segment>
                    </annotations>
                </unit>
            </file>
        </text>
    </corpus>
</multicast>
